setup.py
prob11_distributions/Binomialdistribution.py
prob11_distributions/Gaussiandistribution.py
prob11_distributions/Generaldistribution.py
prob11_distributions/__init__.py
prob11_distributions.egg-info/PKG-INFO
prob11_distributions.egg-info/SOURCES.txt
prob11_distributions.egg-info/dependency_links.txt
prob11_distributions.egg-info/not-zip-safe
prob11_distributions.egg-info/top_level.txt