Metadata-Version: 1.0
Name: prob11-distributions
Version: 0.1
Summary: Gaussian distributions
Home-page: UNKNOWN
Author: Emad Tolba
Author-email: abhathy@yahoo.com
License: UNKNOWN
Platform: UNKNOWN
